GPTFast/__init__.py
GPTFast/Core/GPTFast.py
GPTFast/Core/__init__.py
GPTFast/Core/Compile/Compile.py
GPTFast/Core/Compile/__init__.py
GPTFast/Core/Decode/SpeculativeDecode.py
GPTFast/Core/Decode/__init__.py
GPTFast/Core/KVCache/KVCache.py
GPTFast/Core/KVCache/KVCacheModel.py
GPTFast/Core/KVCache/__init__.py
GPTFast/Core/Quantize/Quantize.py
GPTFast/Core/Quantize/Quantizer.py
GPTFast/Core/Quantize/__init__.py
GPTFast/Core/Quantize/quantize_int8.py
GPTFast/Core/Quantize/GPTQ/__init__.py
GPTFast/Core/Quantize/GPTQ/Constants/DType.py
GPTFast/Core/Quantize/GPTQ/Constants/MappingType.py
GPTFast/Core/Quantize/GPTQ/Constants/ZeroPoint.py
GPTFast/Core/Quantize/GPTQ/Constants/__init__.py
GPTFast/Core/Quantize/GPTQ/Functions/__init__.py
GPTFast/Core/Quantize/GPTQ/Functions/choose_qparams_affine.py
GPTFast/Core/Quantize/GPTQ/Functions/dequantize_affine.py
GPTFast/Core/Quantize/GPTQ/Functions/get_and_check_qmin_qmax.py
GPTFast/Core/Quantize/GPTQ/Functions/get_reduction_params.py
GPTFast/Core/Quantize/GPTQ/Functions/linear_forward_int4.py
GPTFast/Core/Quantize/GPTQ/Functions/quantize_affine.py
GPTFast/Core/Quantize/GPTQ/Modules/WeightOnlyInt4Linear.py
GPTFast/Core/Quantize/GPTQ/Modules/__init__.py
GPTFast/Core/Quantize/GPTQ/Quantizers/GPTQLinearModuleQuantizer.py
GPTFast/Core/Quantize/GPTQ/Quantizers/GPTQModelQuantizer.py
GPTFast/Core/Quantize/GPTQ/Quantizers/GPTQModelQuantizerNew.py
GPTFast/Core/Quantize/GPTQ/Quantizers/__init__.py
GPTFast/Core/Quantize/INT8/__init__.py
GPTFast/Core/Quantize/INT8/Quantizers/Int8Quantizer.py
GPTFast/Core/Quantize/INT8/Quantizers/__init__.py
GPTFast/Helpers/__init__.py
GPTFast/Helpers/Class/__init__.py
GPTFast/Helpers/Class/add_str_as_func.py
GPTFast/Helpers/Class/get_method_str.py
GPTFast/Helpers/Class/get_nested_attr.py
GPTFast/Helpers/Class/set_nested_attr.py
GPTFast/Helpers/Data/__init__.py
GPTFast/Helpers/Data/collate_data.py
GPTFast/Helpers/Eval/__init__.py
GPTFast/Helpers/Eval/profile_decorator.py
GPTFast/Helpers/Eval/timed.py
gptfast-0.3.1.dist-info/LICENSE
gptfast-0.3.1.dist-info/METADATA
gptfast-0.3.1.dist-info/WHEEL
gptfast-0.3.1.dist-info/top_level.txt
gptfast-0.3.1.dist-info/RECORD
